hfpkg/__init__.py
hfpkg/src/__init__.py
hfpkg/src/calculations.py
hfpkg/src/files.py
hfpkg/test/__init__.py
hfpkg/test/test_calculations.py
hfpkg/test/test_files.py
hfpkg-1.0.0.dist-info/METADATA
hfpkg-1.0.0.dist-info/WHEEL
hfpkg-1.0.0.dist-info/top_level.txt
hfpkg-1.0.0.dist-info/RECORD
