Metadata-Version: 2.1
Name: hfpkg
Version: 1.0.0
Summary: Final Project For AIN 1001
Home-page: https://github.com/hzlbkrc/2201109-finalproject
Author: Fatma Hazal BAKIRCI
Author-email: fatma.bakirci@bahcesehir.edu.tr
